llama_index/llms/gradient/BUILD
llama_index/llms/gradient/__init__.py
llama_index/llms/gradient/base.py
llama_index_llms_gradient-0.1.1.dist-info/METADATA
llama_index_llms_gradient-0.1.1.dist-info/WHEEL
llama_index_llms_gradient-0.1.1.dist-info/RECORD
