Metadata-Version: 2.1
Name: llama-index-llms-gradient
Version: 0.1.1
Summary: llama-index llms gradient integration
License: MIT
Author: Your Name
Author-email: you@example.com
Requires-Python: >=3.8.1,<3.12
Classifier: License :: OSI Approved :: MIT License
Classifier: Programming Language :: Python :: 3
Classifier: Programming Language :: Python :: 3.9
Classifier: Programming Language :: Python :: 3.10
Classifier: Programming Language :: Python :: 3.11
Requires-Dist: gradientai (>=1.6.0,<2.0.0)
Requires-Dist: llama-index-core (>=0.10.1,<0.11.0)
